odoo/addons/account_financial_report_block_pdf/README.rst
odoo/addons/account_financial_report_block_pdf/__init__.py
odoo/addons/account_financial_report_block_pdf/__manifest__.py
odoo/addons/account_financial_report_block_pdf/data/ir_config_param.xml
odoo/addons/account_financial_report_block_pdf/i18n/ca_ES.po
odoo/addons/account_financial_report_block_pdf/i18n/es.po
odoo/addons/account_financial_report_block_pdf/static/description/icon.png
odoo/addons/account_financial_report_block_pdf/wizard/__init__.py
odoo/addons/account_financial_report_block_pdf/wizard/abstract_wizard.py
odoo13_addon_account_financial_report_block_pdf-13.0.1.0.0.dist-info/METADATA
odoo13_addon_account_financial_report_block_pdf-13.0.1.0.0.dist-info/WHEEL
odoo13_addon_account_financial_report_block_pdf-13.0.1.0.0.dist-info/top_level.txt
odoo13_addon_account_financial_report_block_pdf-13.0.1.0.0.dist-info/RECORD
