Metadata-Version: 2.1
Name: odoo13-addon-account_financial_report_block_pdf
Version: 13.0.1.0.0
Requires-Python: >=3.5
Requires-Dist: odoo13-addon-account_financial_report
Requires-Dist: odoo>=13.0a,<13.1dev
Summary: Block the generation of financial PDF reports
Home-page: https://github.com/sygel-technology/sy-account-financial-reporting
License: AGPL-3
Author: Sygel,Odoo Community Association (OCA)
Author-email: support@odoo-community.org
Classifier: Programming Language :: Python
Classifier: Framework :: Odoo
Classifier: Framework :: Odoo :: 13.0
Classifier: License :: OSI Approved :: GNU Affero General Public License v3
